Workbook

Sheet Assumptions
A1: Metric | B1: Year 1 | C1: Year 2 | D1: Year 3 | E1: Year 4 | F1: Year 5
A2: --- GROWTH ---
A3: Towns Live | B3: 3 | C3: 15 | D3: 80 | E3: 200 | F3: 500
A4: NHS/Council Contracts Active | B4: 0 | C4: 1 | D4: 4 | E4: 12 | F4: 30
A5: Strategic Partnerships Active | B5: 0 | C5: 1 | D5: 3 | E5: 8 | F5: 15
A7: --- REVENUE DRIVERS ---
A8: Sponsorship Value per Town (£) | B8: 13000
A9: NHS Contract Value (£) | B9: 50000
A10: Strategic Partner Value (£) | B10: 60000
A11: Premium SaaS Revenue per Town (£) | B11: 800
A12: Ticketing & Events Revenue per Town (£) | B12: 2000
A13: Data Insights Revenue per Town (£) | B13: 0 | C13: 0 | D13: 5000 | E13: 5000 | F13: 5000
A15: --- HEADCOUNT ---
A16: Founders / Execs | B16: 1 | C16: 1 | D16: 2 | E16: 3 | F16: 5
A17: Community Managers | B17: 0.5 | C17: 2 | D17: 5 | E17: 12 | F17: 30
A18: Sales / Enterprise | B18: 0 | C18: 1 | D18: 2 | E18: 5 | F18: 12
A19: Developers / Tech | B19: 1 | C19: 2 | D19: 4 | E19: 8 | F19: 15
A21: --- SALARY ASSUMPTIONS ---
A22: Avg Exec Salary (£) | B22: 60000
A23: Avg Community Mgr Salary (£) | B23: 32000
A24: Avg Sales Salary (£) | B24: 45000
A25: Avg Developer Salary (£) | B25: 60000
A27: --- OPERATIONAL MULTIPLIERS ---
A28: Marketing Spend per Town (£) | B28: 1500 | C28: 1000 | D28: 800 | E28: 600 | F28: 500
A29: Infra Spend per Town (£) | B29: 200
A30: Legal/Ops Fixed Cost (£) | B30: 15000 | C30: 25000 | D30: 40000 | E30: 80000 | F30: 150000

Sheet P&L
A1: Category | B1: Year 1 | C1: Year 2 | D1: Year 3 | E1: Year 4 | F1: Year 5
A2: REVENUE
A3: Local Sponsorships | B3: =Assumptions!B3 * Assumptions!$B$8 | C3: =Assumptions!C3 * Assumptions!$B$8 | D3: =Assumptions!D3 * Assumptions!$B$8 | E3: =Assumptions!E3 * Assumptions!$B$8 | F3: =Assumptions!F3 * Assumptions!$B$8
A4: NHS/Council Contracts | B4: =Assumptions!B4 * Assumptions!$B$9 | C4: =Assumptions!C4 * Assumptions!$B$9 | D4: =Assumptions!D4 * Assumptions!$B$9 | E4: =Assumptions!E4 * Assumptions!$B$9 | F4: =Assumptions!F4 * Assumptions!$B$9
A5: Strategic Partnerships | B5: =Assumptions!B5 * Assumptions!$B$10 | C5: =Assumptions!C5 * Assumptions!$B$10 | D5: =Assumptions!D5 * Assumptions!$B$10 | E5: =Assumptions!E5 * Assumptions!$B$10 | F5: =Assumptions!F5 * Assumptions!$B$10
A6: Premium Leader Tools (SaaS) | B6: =Assumptions!B3 * Assumptions!$B$11 | C6: =Assumptions!C3 * Assumptions!$B$11 | D6: =Assumptions!D3 * Assumptions!$B$11 | E6: =Assumptions!E3 * Assumptions!$B$11 | F6: =Assumptions!F3 * Assumptions!$B$11
A7: Ticketing & Events | B7: =Assumptions!B3 * Assumptions!$B$12 | C7: =Assumptions!C3 * Assumptions!$B$12 | D7: =Assumptions!D3 * Assumptions!$B$12 | E7: =Assumptions!E3 * Assumptions!$B$12 | F7: =Assumptions!F3 * Assumptions!$B$12
A8: Data Insights & API | B8: =Assumptions!B3 * Assumptions!B13 | C8: =Assumptions!C3 * Assumptions!C13 | D8: =Assumptions!D3 * Assumptions!D13 | E8: =Assumptions!E3 * Assumptions!E13 | F8: =Assumptions!F3 * Assumptions!F13
A9: TOTAL REVENUE | B9: =SUM(B3:B8) | C9: =SUM(C3:C8) | D9: =SUM(D3:D8) | E9: =SUM(E3:E8) | F9: =SUM(F3:F8)
A11: COSTS
A12: Total Payroll | B12: =(Assumptions!B16*Assumptions!$B$22)+(Assumptions!B17*Assumptions!$B$23)+(Assumptions!B18*Assumptions!$B$24)+(Assumptions!B19*Assumptions!$B$25) | C12: =(Assumptions!C16*Assumptions!$B$22)+(Assumptions!C17*Assumptions!$B$23)+(Assumptions!C18*Assumptions!$B$24)+(Assumptions!C19*Assumptions!$B$25) | D12: =(Assumptions!D16*Assumptions!$B$22)+(Assumptions!D17*Assumptions!$B$23)+(Assumptions!D18*Assumptions!$B$24)+(Assumptions!D19*Assumptions!$B$25) | E12: =(Assumptions!E16*Assumptions!$B$22)+(Assumptions!E17*Assumptions!$B$23)+(Assumptions!E18*Assumptions!$B$24)+(Assumptions!E19*Assumptions!$B$25) | F12: =(Assumptions!F16*Assumptions!$B$22)+(Assumptions!F17*Assumptions!$B$23)+(Assumptions!F18*Assumptions!$B$24)+(Assumptions!F19*Assumptions!$B$25)
A13: Marketing & Local Activation | B13: =Assumptions!B3 * Assumptions!B28 | C13: =Assumptions!C3 * Assumptions!C28 | D13: =Assumptions!D3 * Assumptions!D28 | E13: =Assumptions!E3 * Assumptions!E28 | F13: =Assumptions!F3 * Assumptions!F28
A14: Infrastructure & Hosting | B14: =Assumptions!B3 * Assumptions!$B$29 | C14: =Assumptions!C3 * Assumptions!$B$29 | D14: =Assumptions!D3 * Assumptions!$B$29 | E14: =Assumptions!E3 * Assumptions!$B$29 | F14: =Assumptions!F3 * Assumptions!$B$29
A15: Legal, Ops & Office | B15: =Assumptions!B30 | C15: =Assumptions!C30 | D15: =Assumptions!D30 | E15: =Assumptions!E30 | F15: =Assumptions!F30
A16: TOTAL COSTS | B16: =SUM(B12:B15) | C16: =SUM(C12:C15) | D16: =SUM(D12:D15) | E16: =SUM(E12:E15) | F16: =SUM(F12:F15)
A18: EBITDA (NET PROFIT) | B18: =B9 - B16 | C18: =C9 - C16 | D18: =D9 - D16 | E18: =E9 - E16 | F18: =F9 - F16
A19: EBITDA Margin (%) | B19: =IF(B9=0,0,B18/B9) | C19: =IF(C9=0,0,C18/C9) | D19: =IF(D9=0,0,D18/D9) | E19: =IF(E9=0,0,E18/E9) | F19: =IF(F9=0,0,F18/F9)
